nxml2txt/__init__.py
nxml2txt/data/entities.dat
nxml2txt/extracttex.py
nxml2txt/main.py
nxml2txt/nxmldoc.py
nxml2txt/respace.py
nxml2txt/rewritemmla.py
nxml2txt/rewritetex.py
nxml2txt/rewriteu2a.py
nxml2txt/standoff.py
nxml2txt/txt2clean.py
nxml2txt-0.1.7.dist-info/LICENSE
nxml2txt-0.1.7.dist-info/METADATA
nxml2txt-0.1.7.dist-info/WHEEL
nxml2txt-0.1.7.dist-info/RECORD
